{
  "bios": {
    "1079429121": {
      "step": "pending",
      "country": "Aldemar",
      "flow_type": "bio",
      "job": "شورای بازرگانان",
      "expires_at": "2025-08-09T15:38:57.431203",
      "name": "Florentine Adrianus",
      "nickname": "Black Fish",
      "age": "31",
      "skills": [
        "داروشناسی",
        "سم شناسی",
        "مدیریت امور داخلی",
        "ساخت دارو و سم",
        "کشتی سازی"
      ],
      "skills_description_sent": true,
      "skill_page": 1,
      "skill1": "داروشناسی",
      "skill2": "سم شناسی",
      "skill3": "مدیریت امور داخلی",
      "skill4": "ساخت دارو و سم",
      "skill5": "کشتی سازی",
      "appearance": "پوششی اشرافی و نجیب‌زاده، قد بلند و پوستی روشن، با هیکلی معمولی",
      "history": "فلورنتاین، فرزند دوم دوکی از سرزمین‌های همسایه ( آزور) بود که پس از فارغ‌التحصیلی از دانشکده افسری، راهش رو از مسیر سایر خانواده جدا، و مسیر یک بازرگان موفق رو به پیش گرفت تا در نهایت در جمهوری آلدمر، با موفقیت‌های تجاری و سیاسی که بدست اورد، اکنون به عنوان یکی از پنج عضو شورای بازرگانی شروع به فعالیت می‌کند.",
      "id_number": "@Jmobasher99",
      "user_id_tag": "#Florentin",
      "photo": "AgACAgQAAxkBAAIZM2iXYhQiTEovh5qN1Sye6WY14zmsAAJ3yDEbdXvBUJJgP8i-yZPIAQADAgADeQADNgQ",
      "level": 1,
      "unique_id": "1079429121",
      "saved_at": "2025-08-09T15:12:10.162285"
    },
    "7992768693": {
      "country": "Alestria",
      "job": "مشاور اعظم",
      "step": "asking_nickname",
      "flow_type": "bio",
      "saved_at": "2025-08-10T08:12:13.309046",
      "expires_at": "2025-08-10T08:42:04.345390",
      "name": "Anna"
    },
    "106647374": {
      "country": "Alpyr",
      "job": "مشاور وزارت",
      "step": "asking_age",
      "flow_type": "bio",
      "saved_at": "2025-08-13T20:02:14.794766",
      "expires_at": "2025-08-13T20:32:02.417141",
      "name": "Kavus",
      "nickname": "-"
    },
    "7465909250": {
      "step": "pending",
      "country": "Alestria",
      "flow_type": "bio",
      "job": "مشاغل آزاد",
      "expires_at": "2025-08-15T08:04:54.534367",
      "name": "Charllet",
      "nickname": "Rainy",
      "age": "18",
      "skills": [
        "ستاره شناسی",
        "نوازندگی",
        "حس ششم"
      ],
      "skills_description_sent": true,
      "skill_page": 3,
      "skill1": "ستاره شناسی",
      "skill2": "نوازندگی",
      "skill3": "حس ششم",
      "appearance": "موهای بلند سفید\nدم و گوش گربه‌ای\nبال های فرشته مانند\nقد حدود ۱۶۰",
      "history": "بخاطر مشکلات گذشته کمی شخصیت ارومی هستی",
      "id_number": "@Meiskskjz",
      "user_id_tag": "#charllet",
      "photo": "AgACAgQAAxkBAAI78mie5KuFbY9vVsDmoW3CM07TrfzXAAI9yDEbZuH4UOZBOBgZkLZjAQADAgADeQADNgQ",
      "level": 1,
      "unique_id": "7465909250",
      "saved_at": "2025-08-15T07:41:32.133679"
    },
    "7645102696": {
      "country": "Alestria",
      "job": "مشاغل آزاد",
      "step": "asking_history",
      "flow_type": "bio",
      "saved_at": "2025-08-15T07:51:05.394879",
      "expires_at": "2025-08-15T08:16:38.764325",
      "name": "garo",
      "nickname": "soul",
      "age": "28",
      "skills": [
        "قدرت بدنی بالا",
        "مقاومت در برابر سم",
        "مهارت کار با خنجر"
      ],
      "skills_description_sent": true,
      "skill_page": 0,
      "skill1": "قدرت بدنی بالا",
      "skill2": "مقاومت در برابر سم",
      "skill3": "مهارت کار با خنجر",
      "appearance": "چشمان قرمز \nکویه سیاه رنگ\nقدی بلند و بدنی ورزیده \nدارایه خالکوبی هایه متعدد رو کل دو دست و قسمت کمر"
    }
  },
  "used_hashtags": [
    "#kenway",
    "#Izod",
    "#Valerie",
    "#nezhan",
    "#Elegard",
    "#Padre",
    "#Anna",
    "#leo",
    "#Hory",
    "#heart_of_the_sea",
    "#Shi",
    "#Kaizar",
    "#Zelikor",
    "#Volnir",
    "#eiuw",
    "#Ragnar",
    "#Daniyal_Raz",
    "#Thalia",
    "#Oraya",
    "#stavroula",
    "#LadyDAstre",
    "#Kinoki",
    "#Viana",
    "#Andrew",
    "#TheFool",
    "#mil",
    "#Alisan",
    "#Tsuki",
    "#Jang_uk",
    "#Edward",
    "#Maximus",
    "#mahan",
    "#raiga",
    "#Akai",
    "#W_Z",
    "#Ogami",
    "#Artyom",
    "#Artemis",
    "#sia",
    "#bea",
    "#Beast",
    "#Diana",
    "#Valentina",
    "#TheSilver",
    "#haha",
    "#Florentine",
    "#Alek",
    "#Florentin",
    "#Atalanta",
    "#kazuto",
    "#Ghostblade",
    "#Ghostblad",
    "#Walter",
    "#ansel",
    "#natrix",
    "#nat",
    "#Esmeralda",
    "#Shadow",
    "#Kinoko",
    "#Ernest",
    "#Ash",
    "#Amaryallis",
    "#Ivar",
    "#Emerald",
    "#Enchantress",
    "#cannelleshi",
    "#Queen",
    "#ELIZ",
    "#Damian",
    "#Henry",
    "#SUN",
    "#charllet"
  ]
}